Metadata-Version: 1.1
Name: anime-enforce
Version: 0.1.1
Summary: Unofficial API for animeforce.org.
Home-page: https://github.com/kyraminol/anime-enforce
Author: Kyraminol Endyeran
Author-email: kyraminari@gmail.com
License: UNKNOWN
Keywords: api anime animeforce.org
Platform: UNKNOWN
Classifier: Development Status :: 3 - Alpha
Classifier: Intended Audience :: Developers
Classifier: Operating System :: OS Independent
Classifier: Programming Language :: Python :: 3.5
Classifier: Programming Language :: Python :: 3.6
Classifier: Topic :: Internet
Classifier: Topic :: Software Development :: Libraries :: Python Modules
Classifier: Topic :: Utilities
